colorname/__init__.py
colorname/core.py
color_name-0.2.0.dist-info/LICENSE.md
color_name-0.2.0.dist-info/METADATA
color_name-0.2.0.dist-info/WHEEL
color_name-0.2.0.dist-info/top_level.txt
color_name-0.2.0.dist-info/RECORD
