Metadata-Version: 2.1
Name: color-name
Version: 0.2.0
Summary: Tells you what name a color has
Home-page: https://github.com/tvanderplas/color-name
Author: Tim Vanderplas
License: GPLv3
Platform: UNKNOWN
Classifier: License :: OSI Approved :: GNU General Public License v3 or later (GPLv3+)
Classifier: Programming Language :: Python :: 3
Classifier: Programming Language :: Python :: 3.9
Requires-Dist: pillow
